<net>

   <edges no="8">1i 1o 2i 2o 3i 3o 4i 4o</edges>
   <node_count>5</node_count>


   <edge id="1i" Length="496.90" Speed="19.44" Name="1i" NoLanes="1" XFrom="0.00" YFrom="500.00" XTo="500.00" YTo="500.00" From="1" To="0" Priority="78" Angle="270.00" Type="" function="normal">
      <lanes>
         <lane id="1i_0" depart="1" maxspeed="19.44" length="496.90" changeurge="0">-1.65,498.35 495.25,498.35</lane>
      </lanes>
      <cedge id="3o" via=":0">1i_0</cedge>
      <cedge id="2o" via=":0">1i_0</cedge>
      <cedge id="4o" via=":0">1i_0</cedge>
      <cedge id="1o" via=":0">1i_0</cedge>
   </edge>

   <edge id="1o" Length="493.60" Speed="11.11" Name="1o" NoLanes="1" XFrom="500.00" YFrom="500.00" XTo="0.00" YTo="500.00" From="0" To="1" Priority="46" Angle="90.00" Type="" function="normal">
      <lanes>
         <lane id="1o_0" depart="1" maxspeed="11.11" length="493.60" changeurge="0">495.25,501.65 1.65,501.65</lane>
      </lanes>
      <cedge id="1i" via=":1">1o_0</cedge>
   </edge>

   <edge id="2i" Length="496.90" Speed="19.44" Name="2i" NoLanes="1" XFrom="1000.00" YFrom="500.00" XTo="500.00" YTo="500.00" From="2" To="0" Priority="78" Angle="90.00" Type="" function="normal">
      <lanes>
         <lane id="2i_0" depart="1" maxspeed="19.44" length="496.90" changeurge="0">1001.65,501.65 504.75,501.65</lane>
      </lanes>
      <cedge id="4o" via=":0">2i_0</cedge>
      <cedge id="1o" via=":0">2i_0</cedge>
      <cedge id="3o" via=":0">2i_0</cedge>
      <cedge id="2o" via=":0">2i_0</cedge>
   </edge>

   <edge id="2o" Length="493.60" Speed="11.11" Name="2o" NoLanes="1" XFrom="500.00" YFrom="500.00" XTo="1000.00" YTo="500.00" From="0" To="2" Priority="46" Angle="270.00" Type="" function="normal">
      <lanes>
         <lane id="2o_0" depart="1" maxspeed="11.11" length="493.60" changeurge="0">504.75,498.35 998.35,498.35</lane>
      </lanes>
      <cedge id="2i" via=":2">2o_0</cedge>
   </edge>

   <edge id="3i" Length="496.90" Speed="19.44" Name="3i" NoLanes="1" XFrom="500.00" YFrom="0.00" XTo="500.00" YTo="500.00" From="3" To="0" Priority="78" Angle="180.00" Type="" function="normal">
      <lanes>
         <lane id="3i_0" depart="1" maxspeed="19.44" length="496.90" changeurge="0">501.65,-1.65 501.65,495.25</lane>
      </lanes>
      <cedge id="2o" via=":0">3i_0</cedge>
      <cedge id="4o" via=":0">3i_0</cedge>
      <cedge id="1o" via=":0">3i_0</cedge>
      <cedge id="3o" via=":0">3i_0</cedge>
   </edge>

   <edge id="3o" Length="493.60" Speed="11.11" Name="3o" NoLanes="1" XFrom="500.00" YFrom="500.00" XTo="500.00" YTo="0.00" From="0" To="3" Priority="46" Angle="0.00" Type="" function="normal">
      <lanes>
         <lane id="3o_0" depart="1" maxspeed="11.11" length="493.60" changeurge="0">498.35,495.25 498.35,1.65</lane>
      </lanes>
      <cedge id="3i" via=":3">3o_0</cedge>
   </edge>

   <edge id="4i" Length="496.90" Speed="19.44" Name="4i" NoLanes="1" XFrom="500.00" YFrom="1000.00" XTo="500.00" YTo="500.00" From="4" To="0" Priority="78" Angle="0.00" Type="" function="normal">
      <lanes>
         <lane id="4i_0" depart="1" maxspeed="19.44" length="496.90" changeurge="0">498.35,1001.65 498.35,504.75</lane>
      </lanes>
      <cedge id="1o" via=":0">4i_0</cedge>
      <cedge id="3o" via=":0">4i_0</cedge>
      <cedge id="2o" via=":0">4i_0</cedge>
      <cedge id="4o" via=":0">4i_0</cedge>
   </edge>

   <edge id="4o" Length="493.60" Speed="11.11" Name="4o" NoLanes="1" XFrom="500.00" YFrom="500.00" XTo="500.00" YTo="1000.00" From="0" To="4" Priority="46" Angle="180.00" Type="" function="normal">
      <lanes>
         <lane id="4o_0" depart="1" maxspeed="11.11" length="493.60" changeurge="0">501.65,504.75 501.65,998.35</lane>
      </lanes>
      <cedge id="4i" via=":4">4o_0</cedge>
   </edge>


   <row-logic>
      <key>0</key>
      <requestsize>16</requestsize>
      <lanenumber>4</lanenumber>
      <logic>
         <logicitem request="0" response="0000000000000000" foes="1000010000100000"/>
         <logicitem request="1" response="0111000000000000" foes="0111110001100000"/>
         <logicitem request="2" response="0110001100000000" foes="0110001111100000"/>
         <logicitem request="3" response="0100001000010000" foes="0100001000010000"/>
         <logicitem request="4" response="0000000000000000" foes="0100001000001000"/>
         <logicitem request="5" response="0000000000000111" foes="1100011000000111"/>
         <logicitem request="6" response="0011000000000110" foes="0011111000000110"/>
         <logicitem request="7" response="0010000100000100" foes="0010000100000100"/>
         <logicitem request="8" response="0000000000000000" foes="0010000010000100"/>
         <logicitem request="9" response="0000000001110000" foes="0110000001111100"/>
         <logicitem request="10" response="0000000001100011" foes="1110000001100011"/>
         <logicitem request="11" response="0001000001000010" foes="0001000001000010"/>
         <logicitem request="12" response="0000000000000000" foes="0000100001000010"/>
         <logicitem request="13" response="0000011100000000" foes="0000011111000110"/>
         <logicitem request="14" response="0000011000110000" foes="0000011000111110"/>
         <logicitem request="15" response="0000010000100001" foes="0000010000100001"/>
      </logic>
   </row-logic>

   <row-logic>
      <key>1</key>
      <requestsize>1</requestsize>
      <lanenumber>1</lanenumber>
      <logic>
         <logicitem request="0" response="0" foes="0"/>
      </logic>
   </row-logic>

   <row-logic>
      <key>2</key>
      <requestsize>1</requestsize>
      <lanenumber>1</lanenumber>
      <logic>
         <logicitem request="0" response="0" foes="0"/>
      </logic>
   </row-logic>

   <row-logic>
      <key>3</key>
      <requestsize>1</requestsize>
      <lanenumber>1</lanenumber>
      <logic>
         <logicitem request="0" response="0" foes="0"/>
      </logic>
   </row-logic>

   <row-logic>
      <key>4</key>
      <requestsize>1</requestsize>
      <lanenumber>1</lanenumber>
      <logic>
         <logicitem request="0" response="0" foes="0"/>
      </logic>
   </row-logic>


   <tl-logic type="static">
      <key>0</key>
      <logicno>0</logicno>
      <phaseno>8</phaseno>
      <offset>0</offset>
      <inclanes>1i_0 2i_0 3i_0 4i_0</inclanes>
      <phase duration="20" phase="0000111100001111" brake="1111110011111100" yellow="0000000000000000"/>
      <phase duration="6" phase="0000110000001100" brake="1111111111111111" yellow="0000001100000011"/>
      <phase duration="3" phase="0000110000001100" brake="1111001111110011" yellow="0000000000000000"/>
      <phase duration="6" phase="0000000000000000" brake="1111111111111111" yellow="0000110000001100"/>
      <phase duration="20" phase="1111000011110000" brake="1100111111001111" yellow="0000000000000000"/>
      <phase duration="6" phase="1100000011000000" brake="1111111111111111" yellow="0011000000110000"/>
      <phase duration="3" phase="1100000011000000" brake="0011111100111111" yellow="0000000000000000"/>
      <phase duration="6" phase="0000000000000000" brake="1111111111111111" yellow="1100000011000000"/>
   </tl-logic>


   <junction id="0" type="priority" x="500.00" y="500.00">
      <inclanes>4i_0 2i_0 3i_0 1i_0</inclanes>
      <shape>496.75,504.75 503.25,504.75 504.75,503.25 504.75,496.75 503.25,495.25 496.75,495.25 495.25,496.75 495.25,503.25</shape>
   </junction>

   <junction id="1" type="priority" x="0.00" y="500.00">
      <inclanes>1o_0</inclanes>
      <shape>-0.05,499.95 -3.25,496.75 3.25,503.25 0.05,500.05</shape>
   </junction>

   <junction id="2" type="priority" x="1000.00" y="500.00">
      <inclanes>2o_0</inclanes>
      <shape>1000.05,500.05 1003.25,503.25 996.75,496.75 999.95,499.95</shape>
   </junction>

   <junction id="3" type="priority" x="500.00" y="0.00">
      <inclanes>3o_0</inclanes>
      <shape>500.05,-0.05 503.25,-3.25 496.75,3.25 499.95,0.05</shape>
   </junction>

   <junction id="4" type="priority" x="500.00" y="1000.00">
      <inclanes>4o_0</inclanes>
      <shape>499.95,1000.05 496.75,1003.25 503.25,996.75 500.05,999.95</shape>
   </junction>


   <succ edge="1i" lane="1i_0" junction="0">
      <succlane lane="3o_0" via=":0_12_0" tl="0" linkno="12" yield="1" dir="r" state="t"/>
      <succlane lane="2o_0" via=":0_13_0" tl="0" linkno="13" yield="1" dir="s" state="t"/>
      <succlane lane="4o_0" via=":0_14_0" tl="0" linkno="14" yield="1" dir="l" state="t"/>
      <succlane lane="1o_0" via=":0_15_0" tl="0" linkno="15" yield="1" dir="t" state="t"/>
   </succ>

   <succ edge="1o" lane="1o_0" junction="1">
      <succlane lane="1i_0" via=":1_0_0" yield="0" dir="t" state="M"/>
   </succ>

   <succ edge="2i" lane="2i_0" junction="0">
      <succlane lane="4o_0" via=":0_4_0" tl="0" linkno="4" yield="1" dir="r" state="t"/>
      <succlane lane="1o_0" via=":0_5_0" tl="0" linkno="5" yield="1" dir="s" state="t"/>
      <succlane lane="3o_0" via=":0_6_0" tl="0" linkno="6" yield="1" dir="l" state="t"/>
      <succlane lane="2o_0" via=":0_7_0" tl="0" linkno="7" yield="1" dir="t" state="t"/>
   </succ>

   <succ edge="2o" lane="2o_0" junction="2">
      <succlane lane="2i_0" via=":2_0_0" yield="0" dir="t" state="M"/>
   </succ>

   <succ edge="3i" lane="3i_0" junction="0">
      <succlane lane="2o_0" via=":0_8_0" tl="0" linkno="8" yield="1" dir="r" state="t"/>
      <succlane lane="4o_0" via=":0_9_0" tl="0" linkno="9" yield="1" dir="s" state="t"/>
      <succlane lane="1o_0" via=":0_10_0" tl="0" linkno="10" yield="1" dir="l" state="t"/>
      <succlane lane="3o_0" via=":0_11_0" tl="0" linkno="11" yield="1" dir="t" state="t"/>
   </succ>

   <succ edge="3o" lane="3o_0" junction="3">
      <succlane lane="3i_0" via=":3_0_0" yield="0" dir="t" state="M"/>
   </succ>

   <succ edge="4i" lane="4i_0" junction="0">
      <succlane lane="1o_0" via=":0_0_0" tl="0" linkno="0" yield="1" dir="r" state="t"/>
      <succlane lane="3o_0" via=":0_1_0" tl="0" linkno="1" yield="1" dir="s" state="t"/>
      <succlane lane="2o_0" via=":0_2_0" tl="0" linkno="2" yield="1" dir="l" state="t"/>
      <succlane lane="4o_0" via=":0_3_0" tl="0" linkno="3" yield="1" dir="t" state="t"/>
   </succ>

   <succ edge="4o" lane="4o_0" junction="4">
      <succlane lane="4i_0" via=":4_0_0" yield="0" dir="t" state="M"/>
   </succ>


</net>
